<?xml version="1.0" encoding="UTF-8" standalone="no"?>
<!DOCTYPE tiles-definitions PUBLIC "-//Apache Software Foundation//DTD Tiles Configuration 2.1//EN" "http://tiles.apache.org/dtds/tiles-config_2_1.dtd">
<tiles-definitions>
    <definition extends="default" name="jemsorganizations/list">
        <put-attribute name="body" value="/WEB-INF/views/jemsorganizations/list.jspx"/>
    </definition>
<definition extends="default" name="jemsorganizations/show">
        <put-attribute name="body" value="/WEB-INF/views/jemsorganizations/show.jspx"/>
    </definition>
<definition extends="default" name="jemsorganizations/create">
        <put-attribute name="body" value="/WEB-INF/views/jemsorganizations/create.jspx"/>
    </definition>
<definition extends="default" name="jemsorganizations/update">
        <put-attribute name="body" value="/WEB-INF/views/jemsorganizations/update.jspx"/>
    </definition>
</tiles-definitions>
